{
    "grammarList":
    [
        {
            "type" : "ios",
            "providerName" : "SILManager",
            "dataTypes" : 
            {
                "str" : "NSString *",
                "int" : "NSInteger",
                "uint" : "NSUInteger",
                "long" : "NSInteger",                
                "ulong" : "NSUInteger"
            },
            "dataPlaceHolders" :
            {
                "str" : "%@",
                "int" : "%l",
                "uint" : "%lu",
                "long" : "%l" ,       
                "ulong" : "%lu"
            },         
            "importsH" :
            [
                "<Foundation/Foundation.h>"
            ],
            "importsM" :
            [
                "\"SILRequester.h\""
            ]
        },
        {
            "type" : "android",
            "providerPackage" : "com.silver6wings",
            "providerName" : "SilverProtoBaseProvider",
            "protoHandler" : "SilverProtoHandler",
            "dataTypes" : 
            {
                "str" : "String",
                "int" : "Integer",
                "uint" : "Integer",
                "long" : "Long",                           
                "ulong" : "Long"
            },
            "imports" :
            [
                "com.silver6wings.protobuffer.SilverProtoBaseProvider",
                "com.silver6wings.protobuffer.SilverProtoHandler",
                "com.silver6wings.protobuffer.SilverProtoManager",
                "com.silver6wings.protobuffer.SilverProtoRequester"
            ]
        }
    ]
}
